awscli_local_win/__init__.py
awscli_local_win/__main__.py
awscli_local_win-0.26.0.dist-info/LICENSE
awscli_local_win-0.26.0.dist-info/METADATA
awscli_local_win-0.26.0.dist-info/WHEEL
awscli_local_win-0.26.0.dist-info/entry_points.txt
awscli_local_win-0.26.0.dist-info/top_level.txt
awscli_local_win-0.26.0.dist-info/RECORD
