Metadata-Version: 2.1
Name: awscli-local-win
Version: 0.26.0
Summary: Thin wrapper around the 'aws' command line interface for use with LocalStack *for Windows*.
Author: LocalStack Team
Author-email: Matthew Martin <matthewdeanmartin@gmail.com>
License: Apache License 2.0
Project-URL: homepage, https://github.com/matthewdeanmartin/awscli-local
Keywords: aws,localstack,cli,windows
Classifier: Programming Language :: Python :: 2
Classifier: Programming Language :: Python :: 2.6
Classifier: Programming Language :: Python :: 2.7
Classifier: Programming Language :: Python :: 3
Classifier: Programming Language :: Python :: 3.3
Classifier: Programming Language :: Python :: 3.6
Classifier: Programming Language :: Python :: 3.7
Classifier: Programming Language :: Python :: 3.8
Classifier: Programming Language :: Python :: 3.9
Classifier: License :: OSI Approved :: Apache Software License
Classifier: Topic :: Software Development :: Testing
License-File: LICENSE
Requires-Dist: localstack-client
Requires-Dist: boto3
Provides-Extra: ver1
Requires-Dist: awscli; extra == "ver1"
